{"UlV2D4ob4h+rKlaMdZiTAQ==":"achtergrond-2000x1113.png","8UIhtKDxYiGPZ3rf0PbxEA==":"achtergrond-2000x1102.png","U12cl9kh+rLNmlBnUaxlnw==":"achtergrond-2000x1125.png","2Hyt+1Q5kSehRM/uUs09KA==":"0007-2000x1391.jpg","IKLRIN3we+yzmU/KBGeCJA==":"gif1.gif","03L0kZlcHQ5OmuMtGkwOtg==":"mm%20food-1400x1400.png","rPysdY46eaeCUmvbluWHCA==":"hearts-of-darkness_gilles-van-bever-1400x2033.png","8qt/+msJ+aMciOSNM0VYrg==":"sint-lucas-dag_gilles-van-bever-1400x2032.png","xkhRKnx1PRvlSbkss/+JVg==":"gif1-1.gif","c2S+4ZRGHMvJIjaBmTmUbw==":"hearts-of-darkness_gilles-van-bever-1400x2032.png","xQLiMgvjfVvy6Tt0KwWh2w==":"sint-lucas-dag_gilles-van-bever-1400x2032.jpg","M+PFkcjpUgAGjwe6n0mr8g==":"gabf_gilles-van-bever-1400x1971.png","mAIlqV4yhvkd69jK56xF5A==":"schaeffer_portfolio-1400x1033.png","pDYooaMRWu0RItJSsJrjyQ==":"hoes_portfolio-1400x729.png","CzAAQqA4TzpwkmStaxpdfA==":"hearts-of-darkness_gilles-van-bever-1-1400x2032.png","fXw7CX8wltXdeO+PqRo8vg==":"gabf2-1400x1980.png","cyQIhky/spE5a9BMFMHTYQ==":"hearts-of-darkness-1400x2032.png","GWiV8/K8ufC/2SGdyPuw0A==":"hearts-of-darkness-reeks-1400x677.png","0nSfqs/KmWypb2P2iouhEA==":"gabf-reeks-1400x1016.png","C9SmRkyRnHdWYM74k7BYRA==":"sint-lucas-dag_gilles-van-bever-1-1400x2032.png"}